{
  "$jason": {
    "head": {
      "title": "Screen-1",
      "actions": {
        "$show": {
          "type": "$render"
        }
      },
      "templates": {
        "body": {
          "sections": [
            {
              "type": "vertical",
              "items": [
                {
                  "type": "button",
                  "text": "Set Global Variable",
                  "style": {
                    "align": "center",
                    "width": "100%",
                    "height": 50,
                    "color": "#ffffff",
                    "background": "#0000ff"
                  },
                  "action": {
                    "type": "$href",
                    "options": {
                      "url": "https://pvybhav.github.io/json/Global_Variables/screen-1.json"
                    }
                  }
                },
                {
                  "type": "label",
                  "text": "EF-Screen-1-TextField --> $global.ef_s1_textField"
                },
                {
                  "type": "label",
                  "text": "EF-Screen-2-TextArea --> $global.ef_s2_TextArea"
                },
                {
                  "type": "label",
                  "text": "EF-Screen-3-Switch --> $global.ef_s3_Switch"
                },
                {
                  "type": "label",
                  "text": "EF-Screen-1-TextField --> $global.ef_s1_textField"
                },
                {
                  "type": "label",
                  "text": "EF-Screen-2-TextArea --> $global.ef_s2_TextArea"
                },
                {
                  "type": "label",
                  "text": "EF-Screen-3-Switch --> $global.ef_s3_Switch"
                },
                {
                  "type": "label",
                  "text": "EF-Screen-1-TextField --> $global.ef_s1_textField"
                },
                {
                  "type": "label",
                  "text": "EF-Screen-2-TextArea --> $global.ef_s2_TextArea"
                },
                {
                  "type": "label",
                  "text": "EF-Screen-3-Switch --> $global.ef_s3_Switch"
                }
              ]
            }
          ]
        }
      }
    }
  }
}