{
  "Page_Heading": "Safety Screen Shift Report",
  "Table1_Headers": [
    {
      "type": "label",
      "value": "Safety Screen-1 Rollers",
      "col_type": "col_name",
      "styles": "table_header_styles center_align table_header_name_styles"
    },
    {
      "type": "label",
      "value": "1",
      "col_type": "col_value",
      "styles": "table_header_styles center_align table_header_value_styles"
    },
    {
      "type": "label",
      "value": "2",
      "col_type": "col_value",
      "styles": "table_header_styles center_align table_header_value_styles"
    },
    {
      "type": "label",
      "value": "3",
      "col_type": "col_value",
      "styles": "table_header_styles center_align table_header_value_styles"
    },
    {
      "type": "label",
      "value": "4",
      "col_type": "col_value",
      "styles": "table_header_styles center_align table_header_value_styles"
    },
    {
      "type": "label",
      "value": "5",
      "col_type": "col_value",
      "styles": "table_header_styles center_align table_header_value_styles"
    },
    {
      "type": "label",
      "value": "6",
      "col_type": "col_value",
      "styles": "table_header_styles center_align table_header_value_styles"
    },
    {
      "type": "label",
      "value": "7",
      "col_type": "col_value",
      "styles": "table_header_styles center_align table_header_value_styles"
    },
    {
      "type": "label",
      "value": "8",
      "col_type": "col_value",
      "styles": "table_header_styles center_align table_header_value_styles"
    },
    {
      "type": "label",
      "value": "9",
      "col_type": "col_value",
      "styles": "table_header_styles center_align table_header_value_styles"
    }
  ],
  "Table2_Headers": [
    {
      "type": "label",
      "value": "",
      "styles": "table_header_styles center_align",
      "width": "25%"
    },
    {
      "type": "label",
      "value": "Turning/Stopped",
      "styles": "table_header_styles center_align",
      "width": "25%"
    },
    {
      "type": "label",
      "value": "Action Required",
      "styles": "table_header_styles center_align",
      "width": "30%"
    },
    {
      "type": "label",
      "value": "Completed",
      "col_type": "col_value",
      "styles": "table_header_styles center_align",
      "width": "20%"
    }
  ],
  "Table1_Body": [
    [
      {
        "fieldName": "Safety Screen-2 Rollers",
        "styles": "table_row_odd_styles black",
        "rowValues": [
          {
            "type": "switch",
            "key": "legend",
            "value": "true",
            "col_type": "col_name",
            "checked": "Turning",
            "unchecked": "Stopped",
            "contentDescription": "",
            "styles": "no_padding switch_styles",
            "width": "37%",
            "height": "10%"
          },
          {
            "type": "switch",
            "key": "1",
            "value": "true",
            "col_type": "col_value",
            "contentDescription": "1",
            "styles": "no_padding switch_styles",
            "width": "7%",
            "height": "10%"
          },
          {
            "type": "switch",
            "key": "2",
            "value": "true",
            "col_type": "col_value",
            "contentDescription": "2",
            "styles": "no_padding switch_styles",
            "width": "7%",
            "height": "10%"
          },
          {
            "type": "switch",
            "key": "3",
            "value": "true",
            "col_type": "col_value",
            "contentDescription": "3",
            "styles": "no_padding switch_styles",
            "width": "7%",
            "height": "10%"
          },
          {
            "type": "switch",
            "key": "4",
            "value": "true",
            "col_type": "col_value",
            "contentDescription": "4",
            "styles": "no_padding switch_styles",
            "width": "7%",
            "height": "10%"
          },
          {
            "type": "switch",
            "key": "5",
            "value": "true",
            "col_type": "col_value",
            "contentDescription": "5",
            "styles": "no_padding switch_styles",
            "width": "7%",
            "height": "10%"
          },
          {
            "type": "switch",
            "key": "6",
            "value": "true",
            "col_type": "col_value",
            "contentDescription": "6",
            "styles": "no_padding switch_styles",
            "width": "7%",
            "height": "10%"
          },
          {
            "type": "switch",
            "key": "7",
            "value": "false",
            "col_type": "col_value",
            "contentDescription": "7",
            "styles": "no_padding switch_styles",
            "width": "7%",
            "height": "10%"
          },
          {
            "type": "switch",
            "key": "8",
            "value": "true",
            "col_type": "col_value",
            "contentDescription": "8",
            "styles": "no_padding switch_styles",
            "width": "7%",
            "height": "10%"
          },
          {
            "type": "switch",
            "key": "9",
            "value": "true",
            "col_type": "col_value",
            "contentDescription": "9",
            "styles": "no_padding switch_styles",
            "width": "7%",
            "height": "10%"
          }
        ]
      }
    ]
  ],
  "Table2_Body": [
    [
      {
        "fieldName": "Spray Bars",
        "styles": "table_row_odd_styles black",
        "rowValues": [
          {
            "type": "label",
            "key": "Spray Bars",
            "value": "Spray Bars",
            "contentDescription": "",
            "styles": "no_padding",
            "width": "25%"
          },
          {
            "type": "switch",
            "key": "legend",
            "value": "true",
            "checked": "Turning",
            "unchecked": "Stopped",
            "contentDescription": "",
            "styles": " no_padding",
            "width": "25%"
          },
          {
            "type": "label",
            "key": "Action Required",
            "value": "",
            "styles": "no_padding",
            "width": "30%"
          },
          {
            "type": "switch",
            "key": "Completed",
            "value": "false",
            "styles": "no_padding switch_styles",
            "width": "20%"
          }
        ]
      }
    ],
    [
      {
        "fieldName": "Cloths",
        "styles": "table_row_even_styles black",
        "rowValues": [
          {
            "type": "label",
            "key": "Cloths",
            "value": "Cloths",
            "contentDescription": "",
            "styles": "no_padding",
            "width": "25%"
          },
          {
            "type": "switch",
            "key": "legend",
            "value": "true",
            "checked": "Turning",
            "unchecked": "Stopped",
            "contentDescription": "",
            "styles": " no_padding",
            "width": "25%"
          },
          {
            "type": "label",
            "key": "Action Required",
            "value": "",
            "styles": "no_padding",
            "width": "30%"
          },
          {
            "type": "switch",
            "key": "Completed",
            "value": "false",
            "styles": "no_padding switch_styles",
            "width": "20%"
          }
        ]
      }
    ],
    [
      {
        "fieldName": "Under-pan",
        "styles": "table_row_odd_styles black",
        "rowValues": [
          {
            "type": "label",
            "key": "Under-pan",
            "value": "Under-pan",
            "contentDescription": "",
            "styles": "no_padding",
            "width": "25%"
          },
          {
            "type": "switch",
            "key": "legend",
            "value": "true",
            "checked": "Turning",
            "unchecked": "Stopped",
            "contentDescription": "",
            "styles": " no_padding",
            "width": "25%"
          },
          {
            "type": "label",
            "key": "Clean under-pan build up",
            "value": "Clean under-pan build up",
            "styles": "no_padding",
            "width": "30%"
          },
          {
            "type": "switch",
            "key": "Completed",
            "value": "true",
            "styles": "no_padding switch_styles",
            "width": "20%"
          }
        ]
      }
    ],
    [
      {
        "fieldName": "Trough, North",
        "styles": "table_row_even_styles black",
        "rowValues": [
          {
            "type": "label",
            "key": "Trough, North",
            "value": "Trough, North",
            "contentDescription": "",
            "styles": "no_padding",
            "width": "25%"
          },
          {
            "type": "switch",
            "key": "legend",
            "value": "true",
            "checked": "Turning",
            "unchecked": "Stopped",
            "contentDescription": "",
            "styles": " no_padding",
            "width": "25%"
          },
          {
            "type": "label",
            "key": "Clean trough buildup",
            "value": "Clean trough buildup",
            "styles": "no_padding",
            "width": "30%"
          },
          {
            "type": "switch",
            "key": "Completed",
            "value": "false",
            "styles": "no_padding switch_styles",
            "width": "20%"
          }
        ]
      }
    ],
    [
      {
        "fieldName": "Trough, South",
        "styles": "table_row_odd_styles black",
        "rowValues": [
          {
            "type": "label",
            "key": "Trough, South",
            "value": "Trough, South",
            "contentDescription": "",
            "styles": "no_padding",
            "width": "25%"
          },
          {
            "type": "switch",
            "key": "legend",
            "value": "true",
            "checked": "Turning",
            "unchecked": "Stopped",
            "contentDescription": "",
            "styles": " no_padding",
            "width": "25%"
          },
          {
            "type": "label",
            "key": "Clean trough buildup",
            "value": "Clean trough buildup",
            "styles": "no_padding",
            "width": "30%"
          },
          {
            "type": "switch",
            "key": "Completed",
            "value": "false",
            "styles": "no_padding switch_styles",
            "width": "20%"
          }
        ]
      }
    ]
  ]
}